func_runner_cli/__init__.py
func_runner_cli/helpers.py
func_runner_cli/main.py
func_runner_cli/models.py
func_runner_cli-0.1.5.dist-info/METADATA
func_runner_cli-0.1.5.dist-info/WHEEL
func_runner_cli-0.1.5.dist-info/entry_points.txt
func_runner_cli-0.1.5.dist-info/RECORD
