Metadata-Version: 2.1
Name: func-runner-cli
Version: 0.1.5
Summary: A command line interface tool for Func Runner.
Author: Matthew Orahood
Author-email: morahood@gmail.com
Requires-Python: >=3.12,<4.0
Classifier: Programming Language :: Python :: 3
Classifier: Programming Language :: Python :: 3.12
Requires-Dist: pydantic (>=2.6.4,<3.0.0)
Requires-Dist: pydantic-settings (>=2.2.1,<3.0.0)
Requires-Dist: pyyaml (>=6.0.1,<7.0.0)
Requires-Dist: requests (>=2.31.0,<3.0.0)
Requires-Dist: typer[all] (>=0.9.0,<0.10.0)
